{
  "config": {
    "tool": "go-flows",
    "regime": "common",
    "model": "xgb",
    "task": "binary",
    "split": "temporal",
    "seed": 4,
    "include_port": false,
    "dataset": "dapt20",
    "n_features": 9,
    "subsample_benign": null,
    "max_train": 400000
  },
  "config_hash": "d8f61eb8247d9a93",
  "git_commit": null,
  "n_train": 41854,
  "n_test": 16610,
  "n_test_unseen_class": 0,
  "features": [
    "duration",
    "pkts_fwd",
    "pkts_bwd",
    "bytes_fwd",
    "bytes_bwd",
    "tot_pkts",
    "tot_bytes",
    "is_tcp",
    "is_udp"
  ],
  "metrics": {
    "macro_f1": 0.5072647736595932,
    "weighted_f1": 0.8262116278431247,
    "balanced_accuracy": 0.5144008612914809,
    "per_class": {
      "0": {
        "precision": 0.8834987593052109,
        "recall": 0.9739451548929768,
        "f1-score": 0.9265198581790977,
        "support": 14623.0
      },
      "1": {
        "precision": 0.22244897959183674,
        "recall": 0.054856567689984904,
        "f1-score": 0.08800968914008882,
        "support": 1987.0
      }
    },
    "fpr": 0.026054845107023182,
    "attack_recall": 0.054856567689984904,
    "attack_precision": 0.22244897959183674,
    "auc_pr": 0.258708850503994,
    "confusion_matrix": [
      [
        14242,
        381
      ],
      [
        1878,
        109
      ]
    ],
    "class_order": [
      "0",
      "1"
    ]
  },
  "feature_importances": {
    "tot_pkts": 0.5016570687294006,
    "tot_bytes": 0.4220888912677765,
    "pkts_bwd": 0.02396107092499733,
    "bytes_bwd": 0.01932171732187271,
    "bytes_fwd": 0.012248449958860874,
    "duration": 0.010732236318290234,
    "pkts_fwd": 0.009990536607801914
  },
  "wall_seconds": 0.6
}