{
  "config": {
    "tool": "tranalyzer",
    "regime": "native",
    "model": "rf",
    "task": "binary",
    "split": "stratified",
    "seed": 4,
    "include_port": false,
    "dataset": "dapt20",
    "n_features": 73,
    "subsample_benign": null,
    "max_train": 400000
  },
  "config_hash": "e580a7182b10bf77",
  "git_commit": null,
  "n_train": 35729,
  "n_test": 15313,
  "n_test_unseen_class": 0,
  "features": [
    "tool_timeFirst",
    "tool_timeLast",
    "tool_duration",
    "tool_numHdrs",
    "tool_srcIPCC",
    "tool_srcPort",
    "tool_dstPort",
    "tool_l4Proto",
    "tool_macPairs",
    "tool_dstPortClassN",
    "tool_pktsSnt",
    "tool_pktsRcvd",
    "tool_padBytesSnt",
    "tool_l7BytesSnt",
    "tool_l7BytesRcvd",
    "tool_minL7PktSz",
    "tool_maxL7PktSz",
    "tool_avgL7PktSz",
    "tool_stdL7PktSz",
    "tool_minIAT",
    "tool_maxIAT",
    "tool_avgIAT",
    "tool_stdIAT",
    "tool_pktps",
    "tool_bytps",
    "tool_pktAsm",
    "tool_bytAsm",
    "tool_ipMindIPID",
    "tool_ipMaxdIPID",
    "tool_ipMinTTL",
    "tool_ipMaxTTL",
    "tool_ipTTLChg",
    "tool_tcpISeqN",
    "tool_tcpPSeqCnt",
    "tool_tcpSeqSntBytes",
    "tool_tcpSeqFaultCnt",
    "tool_tcpPAckCnt",
    "tool_tcpFlwLssAckRcvdBytes",
    "tool_tcpAckFaultCnt",
    "tool_tcpBFlgtMx",
    "tool_tcpInitWinSz",
    "tool_tcpAvgWinSz",
    "tool_tcpMinWinSz",
    "tool_tcpMaxWinSz",
    "tool_tcpWinSzDwnCnt",
    "tool_tcpWinSzUpCnt",
    "tool_tcpWinSzChgDirCnt",
    "tool_tcpWinSzThRt",
    "tool_tcpOptPktCnt",
    "tool_tcpOptCnt",
    "tool_tcpMSS",
    "tool_tcpWS",
    "tool_tcpTmS",
    "tool_tcpTmER",
    "tool_tcpEcI",
    "tool_tcpUtm",
    "tool_tcpBtm",
    "tool_tcpSSASAATrip",
    "tool_tcpRTTAckTripMin",
    "tool_tcpRTTAckTripMax",
    "tool_tcpRTTAckTripAvg",
    "tool_tcpRTTAckTripJitAvg",
    "tool_tcpRTTSseqAA",
    "tool_icmpTCcnt",
    "tool_icmpEchoSuccRatio",
    "tool_connSip",
    "tool_connDip",
    "tool_connSipDip",
    "tool_connSipDprt",
    "tool_connF",
    "tool_connG",
    "tool_connNumPCnt",
    "tool_connNumBCnt"
  ],
  "metrics": {
    "macro_f1": 0.9975524733716656,
    "weighted_f1": 0.9981697198935762,
    "balanced_accuracy": 0.996594696673436,
    "per_class": {
      "0": {
        "precision": 0.9978294842854663,
        "recall": 0.9997390396659708,
        "f1-score": 0.9987833492656644,
        "support": 11496.0
      },
      "1": {
        "precision": 0.9992094861660079,
        "recall": 0.9934503536809012,
        "f1-score": 0.9963215974776668,
        "support": 3817.0
      }
    },
    "fpr": 0.00026096033402922753,
    "attack_recall": 0.9934503536809012,
    "attack_precision": 0.9992094861660079,
    "auc_pr": 0.9999403539282001,
    "confusion_matrix": [
      [
        11493,
        3
      ],
      [
        25,
        3792
      ]
    ],
    "class_order": [
      "0",
      "1"
    ]
  },
  "feature_importances": {
    "tool_connSip": 0.14543305169562834,
    "tool_connDip": 0.06334526267569505,
    "tool_connF": 0.06008926484881955,
    "tool_tcpBtm": 0.05270335896334025,
    "tool_tcpMSS": 0.04906796812096715,
    "tool_tcpMaxWinSz": 0.03700201405453837,
    "tool_tcpInitWinSz": 0.03495679737596741,
    "tool_tcpOptCnt": 0.028610911769377613,
    "tool_timeLast": 0.025743950070963577,
    "tool_tcpUtm": 0.023917665241161234,
    "tool_srcPort": 0.02049263092276959,
    "tool_connNumBCnt": 0.019935545012875002,
    "tool_tcpFlwLssAckRcvdBytes": 0.01989528104013772,
    "tool_tcpSSASAATrip": 0.019730568323079883,
    "tool_timeFirst": 0.01956730160553847,
    "tool_tcpAvgWinSz": 0.01889556176128029,
    "tool_tcpOptPktCnt": 0.01749867594230467,
    "tool_minL7PktSz": 0.015818665357508713,
    "tool_tcpISeqN": 0.015086475492101714,
    "tool_tcpPAckCnt": 0.014978863879125122
  },
  "wall_seconds": 4.1
}