{
  "config": {
    "tool": "joy",
    "regime": "native",
    "model": "mlp",
    "task": "multiclass",
    "split": "stratified",
    "seed": 4,
    "include_port": false,
    "dataset": "cicids2017",
    "n_features": 24,
    "subsample_benign": null,
    "max_train": 400000
  },
  "config_hash": "c23730c0dc14c6a2",
  "git_commit": null,
  "n_train": 400000,
  "n_test": 867639,
  "n_test_unseen_class": 0,
  "features": [
    "tool_pr",
    "tool_sp",
    "tool_dp",
    "tool_bytes_out",
    "tool_num_pkts_out",
    "tool_byte_dist_mean",
    "tool_byte_dist_std",
    "tool_bytes_in",
    "tool_num_pkts_in",
    "tool_derived_fwd_pktsize_mean",
    "tool_derived_fwd_pktsize_std",
    "tool_derived_fwd_pktsize_min",
    "tool_derived_fwd_pktsize_max",
    "tool_derived_fwd_pktsize_n",
    "tool_derived_bwd_pktsize_mean",
    "tool_derived_bwd_pktsize_std",
    "tool_derived_bwd_pktsize_min",
    "tool_derived_bwd_pktsize_max",
    "tool_derived_bwd_pktsize_n",
    "tool_derived_iat_ms_mean",
    "tool_derived_iat_ms_std",
    "tool_derived_iat_ms_min",
    "tool_derived_iat_ms_max",
    "tool_derived_iat_ms_n"
  ],
  "metrics": {
    "macro_f1": 0.6961145318644628,
    "weighted_f1": 0.9869214892124336,
    "balanced_accuracy": 0.6762186129365937,
    "per_class": {
      "BENIGN": {
        "precision": 0.9914123961271213,
        "recall": 0.9974709253258881,
        "f1-score": 0.9944324329916103,
        "support": 722794.0
      },
      "Bot": {
        "precision": 0.9565891472868217,
        "recall": 0.9348484848484848,
        "f1-score": 0.9455938697318008,
        "support": 660.0
      },
      "DDoS": {
        "precision": 0.9493765066515878,
        "recall": 0.9788879342089113,
        "f1-score": 0.9639063892791854,
        "support": 32588.0
      },
      "DoS GoldenEye": {
        "precision": 0.9639091646390916,
        "recall": 0.7142427884615384,
        "f1-score": 0.8205039696237487,
        "support": 3328.0
      },
      "DoS Hulk": {
        "precision": 0.9975214249705932,
        "recall": 0.9666782013963808,
        "f1-score": 0.9818576523492014,
        "support": 49127.0
      },
      "DoS Slowhttptest": {
        "precision": 0.5951498300895891,
        "recall": 0.9603688933200398,
        "f1-score": 0.734884608048827,
        "support": 4012.0
      },
      "DoS slowloris": {
        "precision": 0.9932043910088866,
        "recall": 0.8837209302325582,
        "f1-score": 0.9352695052916564,
        "support": 4300.0
      },
      "FTP-Patator": {
        "precision": 0.9983291562238931,
        "recall": 0.9950041631973355,
        "f1-score": 0.9966638865721434,
        "support": 1201.0
      },
      "Heartbleed": {
        "precision": 1.0,
        "recall": 0.3333333333333333,
        "f1-score": 0.5,
        "support": 12.0
      },
      "Infiltration": {
        "precision": 0.5517241379310345,
        "recall": 0.3902439024390244,
        "f1-score": 0.45714285714285713,
        "support": 41.0
      },
      "PortScan": {
        "precision": 0.9920023832439617,
        "recall": 0.9012908598792422,
        "f1-score": 0.944473534930401,
        "support": 48030.0
      },
      "SSH-Patator": {
        "precision": 0.9910714285714286,
        "recall": 0.9899665551839465,
        "f1-score": 0.9905186837702176,
        "support": 897.0
      },
      "Web Attack - Brute Force": {
        "precision": 0.9545454545454546,
        "recall": 0.09722222222222222,
        "f1-score": 0.17647058823529413,
        "support": 432.0
      },
      "Web Attack - Sql Injection": {
        "precision": 0.0,
        "recall": 0.0,
        "f1-score": 0.0,
        "support": 5.0
      },
      "Web Attack - XSS": {
        "precision": 0.0,
        "recall": 0.0,
        "f1-score": 0.0,
        "support": 212.0
      }
    },
    "confusion_matrix": [
      [
        720966,
        28,
        879,
        12,
        9,
        515,
        14,
        2,
        0,
        11,
        348,
        8,
        2,
        0,
        0
      ],
      [
        43,
        617,
        0,
        0,
        0,
        0,
        0,
        0,
        0,
        0,
        0,
        0,
        0,
        0,
        0
      ],
      [
        0,
        0,
        31900,
        0,
        0,
        686,
        2,
        0,
        0,
        0,
        0,
        0,
        0,
        0,
        0
      ],
      [
        88,
        0,
        2,
        2377,
        109,
        746,
        6,
        0,
        0,
        0,
        0,
        0,
        0,
        0,
        0
      ],
      [
        241,
        0,
        664,
        57,
        47490,
        672,
        3,
        0,
        0,
        0,
        0,
        0,
        0,
        0,
        0
      ],
      [
        19,
        0,
        118,
        19,
        0,
        3853,
        0,
        0,
        0,
        2,
        1,
        0,
        0,
        0,
        0
      ],
      [
        491,
        0,
        6,
        1,
        0,
        2,
        3800,
        0,
        0,
        0,
        0,
        0,
        0,
        0,
        0
      ],
      [
        6,
        0,
        0,
        0,
        0,
        0,
        0,
        1195,
        0,
        0,
        0,
        0,
        0,
        0,
        0
      ],
      [
        8,
        0,
        0,
        0,
        0,
        0,
        0,
        0,
        4,
        0,
        0,
        0,
        0,
        0,
        0
      ],
      [
        25,
        0,
        0,
        0,
        0,
        0,
        0,
        0,
        0,
        16,
        0,
        0,
        0,
        0,
        0
      ],
      [
        4709,
        0,
        32,
        0,
        0,
        0,
        0,
        0,
        0,
        0,
        43289,
        0,
        0,
        0,
        0
      ],
      [
        8,
        0,
        0,
        0,
        0,
        0,
        1,
        0,
        0,
        0,
        0,
        888,
        0,
        0,
        0
      ],
      [
        390,
        0,
        0,
        0,
        0,
        0,
        0,
        0,
        0,
        0,
        0,
        0,
        42,
        0,
        0
      ],
      [
        5,
        0,
        0,
        0,
        0,
        0,
        0,
        0,
        0,
        0,
        0,
        0,
        0,
        0,
        0
      ],
      [
        212,
        0,
        0,
        0,
        0,
        0,
        0,
        0,
        0,
        0,
        0,
        0,
        0,
        0,
        0
      ]
    ],
    "class_order": [
      "BENIGN",
      "Bot",
      "DDoS",
      "DoS GoldenEye",
      "DoS Hulk",
      "DoS Slowhttptest",
      "DoS slowloris",
      "FTP-Patator",
      "Heartbleed",
      "Infiltration",
      "PortScan",
      "SSH-Patator",
      "Web Attack - Brute Force",
      "Web Attack - Sql Injection",
      "Web Attack - XSS"
    ]
  },
  "feature_importances": null,
  "wall_seconds": 39.9
}